{
  "users": [
    {
      "id": 1,
      "name": "Nicolas Soares",
      "cpf": "10553687956",
      "email": "nicolas.soaresh.98@gmail.com",
      "phone": "48984689248",
      "username": "root6439",
      "password": "1234567",
      "admin": true
    },
    {
      "name": "Caroline Kroeger",
      "cpfCnpj": "10294668900",
      "email": "caroline.kroeger@gmail.com",
      "phone": "48991875710",
      "username": "kgcarol",
      "password": "1234567",
      "id": 9,
      "admin": false
    }
  ],
  "products": [
    {
      "id": 1,
      "title": "Consultoria para empresas",
      "description": "Lorem ipsum dolor sit amet, consectetur adipiscing elit. Etiam augue ex, pellentesque non diam quis, vehicula consequat dui. Etiam eleifend tortor ac orci aliquam tristique. ",
      "price": 499.0,
      "urlImage": "./src/assets/images/servico1.jpeg"
    },
    {
      "id": 2,
      "title": "Treinamento pessoal",
      "description": "Este serviço tem foco no desenvolvimento pessoal, aplica-se a pessoas que queiram aprender coisas novas bla bla",
      "price": 349.0,
      "urlImage": "./src/assets/images/servico2.jpeg"
    },
    {
      "id": 3,
      "title": "Treinamento coletivo",
      "description": "Treinamento para várias pessoas com duração de 6 meses bla bla bla",
      "price": 899.0,
      "urlImage": "./src/assets/images/servico3.jpeg"
    },
    {
      "id": 4,
      "title": "Consultoria para empresas",
      "description": "Lorem ipsum dolor sit amet, consectetur adipiscing elit. Etiam augue ex, pellentesque non diam quis, vehicula consequat dui. Etiam eleifend tortor ac orci aliquam tristique. ",
      "price": 499.0,
      "urlImage": "./src/assets/images/servico1.jpeg"
    },
    {
      "id": 5,
      "title": "Treinamento pessoal",
      "description": "Este serviço tem foco no desenvolvimento pessoal, aplica-se a pessoas que queiram aprender coisas novas bla bla",
      "price": 349.0,
      "urlImage": "./src/assets/images/servico2.jpeg"
    },
    {
      "id": 6,
      "title": "Treinamento coletivo",
      "description": "Treinamento para várias pessoas com duração de 6 meses bla bla bla",
      "price": 899.0,
      "urlImage": "./src/assets/images/servico3.jpeg"
    },
    {
      "id": 7,
      "title": "Consultoria para empresas",
      "description": "Lorem ipsum dolor sit amet, consectetur adipiscing elit. Etiam augue ex, pellentesque non diam quis, vehicula consequat dui. Etiam eleifend tortor ac orci aliquam tristique. ",
      "price": 499.0,
      "urlImage": "./src/assets/images/servico1.jpeg"
    },
    {
      "id": 8,
      "title": "Treinamento pessoal",
      "description": "Este serviço tem foco no desenvolvimento pessoal, aplica-se a pessoas que queiram aprender coisas novas bla bla",
      "price": 349.0,
      "urlImage": "./src/assets/images/servico2.jpeg"
    },
    {
      "id": 9,
      "title": "Treinamento coletivo",
      "description": "Treinamento para várias pessoas com duração de 6 meses bla bla bla",
      "price": 899.0,
      "urlImage": "./src/assets/images/servico3.jpeg"
    }
  ],
  "inventory": [
    {
      "id": 1,
      "product": 1,
      "quantity": 10
    }
  ]
}
